[
{
"customer_id":"CUSTOMER001",
"first_name":"Spandan",
"last_name":"Satapathy",
"email":"spnsatapathy1834@gmail.com",
"phone":"9692918347",
"address":"India",
"date_of_birth":"1999-06-18",
"account_balance":5000.50,
"created_at":"2026-03-25"
},
{
"customer_id":"CUSTOMER002",
"first_name":"Test",
"last_name":"Two",
"email":"TestTwo@gmail.com",
"phone":"9692918347",
"address":"India",
"date_of_birth":"1999-06-18",
"account_balance":5000.50,
"created_at":"2026-03-25"
},
{
"customer_id":"CUSTOMER003",
"first_name":"Test",
"last_name":"Three",
"email":"TestThree@gmail.com",
"phone":"9692918347",
"address":"India",
"date_of_birth":"1999-06-18",
"account_balance":5000.50,
"created_at":"2026-03-25"
},
{
"customer_id":"CUSTOMER004",
"first_name":"Test",
"last_name":"Four",
"email":"TestFour@gmail.com",
"phone":"9692918347",
"address":"India",
"date_of_birth":"1999-06-18",
"account_balance":5000.50,
"created_at":"2026-03-25"
},
{
"customer_id":"CUSTOMER005",
"first_name":"Test",
"last_name":"Five",
"email":"TestFive@gmail.com",
"phone":"9692918347",
"address":"India",
"date_of_birth":"1999-06-18",
"account_balance":5000.50,
"created_at":"2026-03-25"
},
{
"customer_id":"CUSTOMER006",
"first_name":"Test",
"last_name":"Six",
"email":"TestSix@gmail.com",
"phone":"9692918347",
"address":"India",
"date_of_birth":"1999-06-18",
"account_balance":5000.50,
"created_at":"2026-03-25"
},
{
"customer_id":"CUSTOMER007",
"first_name":"Test",
"last_name":"Seven",
"email":"TestSeven@gmail.com",
"phone":"9692918347",
"address":"India",
"date_of_birth":"1999-06-18",
"account_balance":5000.50,
"created_at":"2026-03-25"
},
{
"customer_id":"CUSTOMER008",
"first_name":"Test",
"last_name":"Eight",
"email":"TestEight@gmail.com",
"phone":"9692918347",
"address":"India",
"date_of_birth":"1999-06-18",
"account_balance":5000.50,
"created_at":"2026-03-25"
},
{
"customer_id":"CUSTOMER009",
"first_name":"Test",
"last_name":"Nine",
"email":"TestNine@gmail.com",
"phone":"9692918347",
"address":"India",
"date_of_birth":"1999-06-18",
"account_balance":5000.50,
"created_at":"2026-03-25"
},
{
"customer_id":"CUSTOMER010",
"first_name":"Test",
"last_name":"Ten",
"email":"TestTen@gmail.com",
"phone":"9692918347",
"address":"India",
"date_of_birth":"1999-06-18",
"account_balance":5000.50,
"created_at":"2026-03-25"
},
{
"customer_id":"CUSTOMER011",
"first_name":"Test",
"last_name":"Eleven",
"email":"TestEleven@gmail.com",
"phone":"9692918347",
"address":"India",
"date_of_birth":"1999-06-18",
"account_balance":5000.50,
"created_at":"2026-03-25"
},
{
"customer_id":"CUSTOMER012",
"first_name":"Test",
"last_name":"Tweleve",
"email":"TestTwelve@gmail.com",
"phone":"9692918347",
"address":"India",
"date_of_birth":"1999-06-18",
"account_balance":5000.50,
"created_at":"2026-03-25"
},
{
"customer_id":"CUSTOMER013",
"first_name":"Test",
"last_name":"Thirteen",
"email":"TestThirteen@gmail.com",
"phone":"9692918347",
"address":"India",
"date_of_birth":"1999-06-18",
"account_balance":5000.50,
"created_at":"2026-03-25"
},
{
"customer_id":"CUSTOMER014",
"first_name":"Test",
"last_name":"Fourteen",
"email":"TestFourteen@gmail.com",
"phone":"9692918347",
"address":"India",
"date_of_birth":"1999-06-18",
"account_balance":5000.50,
"created_at":"2026-03-25"
},
{
"customer_id":"CUSTOMER015",
"first_name":"Test",
"last_name":"Fifteen",
"email":"TesteFifteen@gmail.com",
"phone":"9692918347",
"address":"India",
"date_of_birth":"1999-06-18",
"account_balance":5000.50,
"created_at":"2026-03-25"
},
{
"customer_id":"CUSTOMER016",
"first_name":"Test",
"last_name":"Sixteen",
"email":"TestSixteen@gmail.com",
"phone":"9692918347",
"address":"India",
"date_of_birth":"1999-06-18",
"account_balance":5000.50,
"created_at":"2026-03-25"
},
{
"customer_id":"CUSTOMER017",
"first_name":"Test",
"last_name":"Seventeen",
"email":"TestSeventeen@gmail.com",
"phone":"9692918347",
"address":"India",
"date_of_birth":"1999-06-18",
"account_balance":5000.50,
"created_at":"2026-03-25"
},
{
"customer_id":"CUSTOMER018",
"first_name":"Test",
"last_name":"Eighteen",
"email":"TestEighteen@gmail.com",
"phone":"9692918347",
"address":"India",
"date_of_birth":"1999-06-18",
"account_balance":5000.50,
"created_at":"2026-03-25"
},
{
"customer_id":"CUSTOMER019",
"first_name":"Test",
"last_name":"Nineteen",
"email":"TestNineteen@gmail.com",
"phone":"9692918347",
"address":"India",
"date_of_birth":"1999-06-18",
"account_balance":5000.50,
"created_at":"2026-03-25"
},
{
"customer_id":"CUSTOMER020",
"first_name":"Test",
"last_name":"Twenty",
"email":"TestTwenty@gmail.com",
"phone":"9692918347",
"address":"India",
"date_of_birth":"1999-06-18",
"account_balance":5000.50,
"created_at":"2026-03-25"
}
]